captcha_pc/__init__.py
captcha_pc/captcha_pc.py
captcha_pc/deathbycaptcha.py
captcha_pc_2-3.0.1.dist-info/LICENSE.txt
captcha_pc_2-3.0.1.dist-info/METADATA
captcha_pc_2-3.0.1.dist-info/WHEEL
captcha_pc_2-3.0.1.dist-info/top_level.txt
captcha_pc_2-3.0.1.dist-info/RECORD
