Metadata-Version: 2.1
Name: captcha-pc-2
Version: 3.0.1
Summary: Função que faz o download de arquivos através de URLs informadas
Home-page: UNKNOWN
License: MIT
Keywords: captcha_pc_2
Platform: UNKNOWN
Classifier: Development Status :: 5 - Production/Stable
Classifier: Intended Audience :: Developers
Classifier: License :: OSI Approved :: MIT License
Classifier: Natural Language :: Portuguese (Brazilian)
Classifier: Operating System :: OS Independent
License-File: LICENSE.txt
